co_mit/__about__.py
co_mit/__init__.py
co_mit/cli.py
co_mit/commit.py
co_mit/config.py
co_mit/tools/__init__.py
co_mit/tools/git.py
co_mit/tools/os.py
co_mit-1.1.0.dist-info/METADATA
co_mit-1.1.0.dist-info/WHEEL
co_mit-1.1.0.dist-info/entry_points.txt
co_mit-1.1.0.dist-info/licenses/LICENSE.txt
co_mit-1.1.0.dist-info/RECORD
