Metadata-Version: 2.4
Name: co-mit
Version: 1.1.0
Summary: help with commits!
Project-URL: Documentation, https://github.com/olincb/commit-helper#readme
Project-URL: Source, https://github.com/olincb/commit-helper
Author-email: "C.B. Olin" <chris.baillie.olin@gmail.com>
License-Expression: MIT
License-File: LICENSE.txt
Keywords: ai,commit,generative,git,helper
Classifier: Development Status :: 4 - Beta
Classifier: Programming Language :: Python
Classifier: Programming Language :: Python :: 3.8
Classifier: Programming Language :: Python :: 3.9
Classifier: Programming Language :: Python :: 3.10
Classifier: Programming Language :: Python :: 3.11
Classifier: Programming Language :: Python :: 3.12
Classifier: Programming Language :: Python :: 3.13
Classifier: Programming Language :: Python :: Implementation :: CPython
Classifier: Programming Language :: Python :: Implementation :: PyPy
Requires-Python: >=3.8
Requires-Dist: llama-index
Requires-Dist: pydantic-settings
Requires-Dist: rich-click
Provides-Extra: dev
Requires-Dist: python-dotenv; extra == 'dev'
Requires-Dist: ruff; extra == 'dev'
